MANIFEST.in
setup.py
P/__init__.py
P/_libs.py
P/cmd.py
P/lang.py
P/pipe.py
mroy_line.egg-info/PKG-INFO
mroy_line.egg-info/SOURCES.txt
mroy_line.egg-info/dependency_links.txt
mroy_line.egg-info/entry_points.txt
mroy_line.egg-info/not-zip-safe
mroy_line.egg-info/requires.txt
mroy_line.egg-info/top_level.txt
zpython/LICENSE
zpython/README.md
zpython/zpython.plugin.zsh