Metadata-Version: 1.0
Name: mroy-line
Version: 0.4.2
Summary: a simple way to use mongo db, let db like dict
Home-page: https://github.com/Qingluan/.git
Author: Froy_Qing
Author-email: darkhackdevil@gmail.com
License: gnu3.0
Platform: UNKNOWN
